{
  "last_updated": "2026-03-31T11:47:40.919021+00:00",
  "sources_checked": 13,
  "sources_successful": 1,
  "source_names": [
    "University Affairs",
    "CSBBCS",
    "HigherEdJobs",
    "CAUT Academic Work",
    "Chronicle of Higher Ed",
    "Academic Careers",
    "Academic Positions",
    "NOSM University",
    "University of British Columbia",
    "University of Waterloo",
    "McGill University",
    "University of Ottawa",
    "Brock University"
  ],
  "jobs": [
    {
      "title": "Limited Term Faculty (LTF) Position in Biology",
      "institution": "",
      "location": "Canada",
      "province": "Unknown",
      "deadline": "August 1, 2026",
      "url": "https://www.academicwork.ca/jobs/limited-term-faculty-ltf-position-in-biology-toronto-metropolitan-university-2",
      "apply_url": "https://www.academicwork.ca/jobs/limited-term-faculty-ltf-position-in-biology-toronto-metropolitan-university-2",
      "match": "partial",
      "source": "CAUT Academic Work",
      "date_posted": ""
    },
    {
      "title": "Limited Term Faculty (LTF) Position in Biology",
      "institution": "",
      "location": "Canada",
      "province": "Unknown",
      "deadline": "August 1, 2026",
      "url": "https://www.academicwork.ca/jobs/limited-term-faculty-ltf-position-in-biology-toronto-metropolitan-university-1",
      "apply_url": "https://www.academicwork.ca/jobs/limited-term-faculty-ltf-position-in-biology-toronto-metropolitan-university-1",
      "match": "partial",
      "source": "CAUT Academic Work",
      "date_posted": ""
    },
    {
      "title": "Limited Term Faculty (LTF) Position in Biology",
      "institution": "",
      "location": "Canada",
      "province": "Unknown",
      "deadline": "August 1, 2026",
      "url": "https://www.travailacademique.ca/jobs/limited-term-faculty-ltf-position-in-biology-toronto-metropolitan-university-2",
      "apply_url": "https://www.travailacademique.ca/jobs/limited-term-faculty-ltf-position-in-biology-toronto-metropolitan-university-2",
      "match": "partial",
      "source": "CAUT Academic Work",
      "date_posted": ""
    },
    {
      "title": "Limited Term Faculty (LTF) Position in Biology",
      "institution": "",
      "location": "Canada",
      "province": "Unknown",
      "deadline": "August 1, 2026",
      "url": "https://www.travailacademique.ca/jobs/limited-term-faculty-ltf-position-in-biology-toronto-metropolitan-university-1",
      "apply_url": "https://www.travailacademique.ca/jobs/limited-term-faculty-ltf-position-in-biology-toronto-metropolitan-university-1",
      "match": "partial",
      "source": "CAUT Academic Work",
      "date_posted": ""
    }
  ]
}